[
  {
    "inputs": [],
    "stateMutability": "payable",
    "type": "constructor"
  },
  {
    "anonymous": false,
    "inputs": [
      {
        "indexed": true,
        "internalType": "address",
        "name": "from",
        "type": "address"
      },
      {
        "indexed": false,
        "internalType": "string",
        "name": "message",
        "type": "string"
      },
      {
        "indexed": false,
        "internalType": "uint256",
        "name": "timestamp",
        "type": "uint256"
      }
    ],
    "name": "NewTweet",
    "type": "event"
  },
  {
    "inputs": [],
    "name": "getAllTweets",
    "outputs": [
      {
        "components": [
          {
            "internalType": "address",
            "name": "from",
            "type": "address"
          },
          {
            "internalType": "string",
            "name": "message",
            "type": "string"
          },
          {
            "internalType": "uint256",
            "name": "timestamp",
            "type": "uint256"
          }
        ],
        "internalType": "struct TwitterFeed.Tweet[]",
        "name": "",
        "type": "tuple[]"
      }
    ],
    "stateMutability": "view",
    "type": "function"
  },
  {
    "inputs": [],
    "name": "getTotalTweets",
    "outputs": [
      {
        "internalType": "uint256",
        "name": "",
        "type": "uint256"
      }
    ],
    "stateMutability": "view",
    "type": "function"
  },
  {
    "inputs": [
      {
        "internalType": "address",
        "name": "",
        "type": "address"
      }
    ],
    "name": "lastTweetedAt",
    "outputs": [
      {
        "internalType": "uint256",
        "name": "",
        "type": "uint256"
      }
    ],
    "stateMutability": "view",
    "type": "function"
  },
  {
    "inputs": [
      {
        "internalType": "string",
        "name": "_message",
        "type": "string"
      }
    ],
    "name": "tweet",
    "outputs": [],
    "stateMutability": "nonpayable",
    "type": "function"
  }
]